sphinxcontrib_pseudocode-0.7.0-py3.8-nspkg.pth
docs/conf.py
env/bin/rst2html.py
env/bin/rst2html4.py
env/bin/rst2html5.py
env/bin/rst2latex.py
env/bin/rst2man.py
env/bin/rst2odt.py
env/bin/rst2odt_prepstyles.py
env/bin/rst2pseudoxml.py
env/bin/rst2s5.py
env/bin/rst2xetex.py
env/bin/rst2xml.py
env/bin/rstpep2html.py
sphinxcontrib/exceptions.py
sphinxcontrib/pseudocode.py
tests/conftest.py
tests/test_html.py
tests/roots/test-basic/conf.py
sphinxcontrib_pseudocode-0.7.0.dist-info/LICENSE.rst
sphinxcontrib_pseudocode-0.7.0.dist-info/METADATA
sphinxcontrib_pseudocode-0.7.0.dist-info/WHEEL
sphinxcontrib_pseudocode-0.7.0.dist-info/namespace_packages.txt
sphinxcontrib_pseudocode-0.7.0.dist-info/top_level.txt
sphinxcontrib_pseudocode-0.7.0.dist-info/RECORD
