Metadata-Version: 2.1
Name: sphinxcontrib-pseudocode
Version: 0.7.0
Summary: write LaTeX algorithm in your sphinx-doc powered docs
Home-page: https://github.com/xxks-kkk/sphinxcontrib-algo/
Author: Zeyuan Hu
Author-email: zeyuan.zack.hu@gmail.com
License: BSD
Platform: any
Classifier: Development Status :: 4 - Beta
Classifier: Environment :: Console
Classifier: Environment :: Web Environment
Classifier: Intended Audience :: Developers
Classifier: License :: OSI Approved :: BSD License
Classifier: Operating System :: OS Independent
Classifier: Programming Language :: Python
Classifier: Programming Language :: Python :: 3
Classifier: Programming Language :: Python :: 3.6
Classifier: Programming Language :: Python :: 3.7
Classifier: Programming Language :: Python :: 3.8
Classifier: Programming Language :: Python :: 3.9
Classifier: Programming Language :: Python :: Implementation :: CPython
Classifier: Programming Language :: Python :: Implementation :: PyPy
Classifier: Topic :: Documentation
Classifier: Topic :: Utilities
License-File: LICENSE.rst
